warc_s3/__init__.py
warc_s3/test_dummy.py
warc_s3-1.0.1.dist-info/LICENSE
warc_s3-1.0.1.dist-info/METADATA
warc_s3-1.0.1.dist-info/WHEEL
warc_s3-1.0.1.dist-info/top_level.txt
warc_s3-1.0.1.dist-info/RECORD
