Metadata-Version: 2.2
Name: warc-s3
Version: 1.0.1
Summary: Scalable and easy WARC records storage on S3.
Author-email: Jan Heinrich Merker <heinrich.merker@uni-jena.de>
Project-URL: Homepage, https://github.com/janheinrichmerker/warc-s3
Project-URL: Bug Tracker, https://github.com/janheinrichmerker/warc-s3/issues
Classifier: Programming Language :: Python :: 3
Classifier: Programming Language :: Python :: 3 :: Only
Classifier: Programming Language :: Python :: 3.8
Classifier: Programming Language :: Python :: 3.9
Classifier: Programming Language :: Python :: 3.10
Classifier: Programming Language :: Python :: 3.11
Classifier: Programming Language :: Python :: 3.12
Classifier: License :: OSI Approved :: MIT License
Classifier: Operating System :: OS Independent
Classifier: Intended Audience :: Science/Research
Classifier: Topic :: Scientific/Engineering
Requires-Python: >=3.8
License-File: LICENSE
Requires-Dist: boto3<=1.35.99,~=1.28
Requires-Dist: importlib-metadata<9.0,>=6.5
Requires-Dist: more-itertools<11.0,>=9.0
Requires-Dist: tqdm~=4.64
Requires-Dist: warcio~=1.7
Provides-Extra: tests
Requires-Dist: bandit[toml]~=1.7; extra == "tests"
Requires-Dist: boto3-stubs[s3]~=1.28; extra == "tests"
Requires-Dist: mypy~=1.6; extra == "tests"
Requires-Dist: pytest<9.0,>=7.2; extra == "tests"
Requires-Dist: pytest-cov<7,>=4; extra == "tests"
Requires-Dist: ruff~=0.2.1; extra == "tests"
Requires-Dist: types-tqdm~=4.66; extra == "tests"
